proxycurl/asyncio/__init__.py
proxycurl/asyncio/base.py
proxycurl/asyncio/library.py
proxycurl/config.py
proxycurl/gevent/__init__.py
proxycurl/gevent/base.py
proxycurl/gevent/library.py
proxycurl/models.py
proxycurl/twisted/__init__.py
proxycurl/twisted/base.py
proxycurl/twisted/library.py
proxycurl-0.0.5.dist-info/WHEEL
proxycurl-0.0.5.dist-info/METADATA
proxycurl-0.0.5.dist-info/RECORD
